{
  "name": "spam",
  "blueprint": {
    "1": {
      "id": 1,
      "name": "Start",
      "class": "start",
      "values": {},
      "inputs": {},
      "outputs": {
        "output_1": [
          {
            "node": "2",
            "output": "input_1"
          }
        ]
      },
      "pos_x": 215,
      "pos_y": 375
    },
    "2": {
      "id": 2,
      "name": "PopupSpam",
      "class": "popupspam",
      "values": {
        "count": "10"
      },
      "inputs": {
        "input_1": [
          {
            "node": "1",
            "input": "output_1"
          }
        ]
      },
      "outputs": {
        "output_1": [
          {
            "node": "3",
            "output": "input_1"
          }
        ]
      },
      "pos_x": 542,
      "pos_y": 397
    },
    "3": {
      "id": 3,
      "name": "End",
      "class": "end",
      "values": {},
      "inputs": {
        "input_1": [
          {
            "node": "2",
            "input": "output_1"
          }
        ]
      },
      "outputs": {},
      "pos_x": 929,
      "pos_y": 442
    }
  }
}